[
    {
      "店名": "炭火焼鳥 鳥吉",
      "ジャンル": "居酒屋",
      "価格帯": "2000～2999",
      "場所": "渋谷駅 徒歩5分",
      "開店時間": "17:00~23:00",
      "席数": 40,
      "予約数": 25
    },
    {
      "店名": "和牛焼肉 うし匠",
      "ジャンル": "焼き肉",
      "価格帯": "3000～4999",
      "場所": "新宿駅 徒歩3分",
      "開店時間": "11:00~23:00",
      "席数": 60,
      "予約数": 45
    },
    {
      "店名": "Trattoria Sole",
      "ジャンル": "イタリアン",
      "価格帯": "1000～1999",
      "場所": "恵比寿駅 徒歩4分",
      "開店時間": "11:30~21:30",
      "席数": 35,
      "予約数": 20
    },
    {
      "店名": "龍華苑",
      "ジャンル": "中華料理",
      "価格帯": "1000～1999",
      "場所": "池袋駅 徒歩6分",
      "開店時間": "10:00~22:00",
      "席数": 50,
      "予約数": 30
    },
    {
      "店名": "江戸前すし 鮨匠",
      "ジャンル": "すし",
      "価格帯": "5000～6999",
      "場所": "東京駅 徒歩2分",
      "開店時間": "12:00~21:00",
      "席数": 20,
      "予約数": 10
    },
    {
      "店名": "Cafe Latte",
      "ジャンル": "カフェ",
      "価格帯": "0～999",
      "場所": "原宿駅 徒歩1分",
      "開店時間": "9:00~19:00",
      "席数": 25,
      "予約数": 5
    },
    {
      "店名": "ファミリーレストラン Smile",
      "ジャンル": "ファミレス",
      "価格帯": "1000～1999",
      "場所": "上野駅 徒歩4分",
      "開店時間": "8:00~22:00",
      "席数": 80,
      "予約数": 35
    },
    {
      "店名": "バーガーハウス Max",
      "ジャンル": "ファストフード",
      "価格帯": "0～999",
      "場所": "品川駅 徒歩3分",
      "開店時間": "10:00~20:00",
      "席数": 50,
      "予約数": 20
    },
    {
      "店名": "韓国家庭料理 チョンガーネ",
      "ジャンル": "韓国料理",
      "価格帯": "2000～2999",
      "場所": "新大久保駅 徒歩2分",
      "開店時間": "11:00~22:30",
      "席数": 40,
      "予約数": 30
    }
  ]
  